Metadata-Version: 2.1
Name: fakeinvoicegen
Version: 0.1.0
Summary: A package to generate fake invoices using Faker and InvoiceGenerator
Home-page: https://github.com/Khushaljethava/fakeinvoicegen
Author: Khushal jethava
Author-email: khushaljethava14@outlook.com
Classifier: Development Status :: 3 - Alpha
Classifier: Intended Audience :: Developers
Classifier: License :: OSI Approved :: MIT License
Classifier: Operating System :: OS Independent
Classifier: Programming Language :: Python :: 3
Classifier: Programming Language :: Python :: 3.7
Classifier: Programming Language :: Python :: 3.8
Classifier: Programming Language :: Python :: 3.9
Requires-Python: >=3.7
License-File: LICENSE
